{
  "version": "1.0",
  "type": "copyright_proof",
  "author": "Artvision.pro",
  "author_details": {
    "company": "Маркетинговое агентство Artvision",
    "location": "Санкт-Петербург, Москва",
    "website": "https://artvision.pro",
    "since": 2007
  },
  "file": {
    "name": "otido-landing-v5.html",
    "original_path": "/mnt/user-data/outputs/landings-protected/otido-landing-v5.html",
    "size_bytes": 72733,
    "hash_algorithm": "SHA-256",
    "hash": "094888b6451fd6ed525d76cf0ad70a0db1bfbe6eb1f890b9298eaa9cf66b7bb8"
  },
  "timestamp": {
    "created": "2025-12-19T14:51:45.053334",
    "timezone": "Europe/Moscow",
    "unix": 1766155905
  },
  "content_fingerprint": {
    "first_100_chars_hash": "bb004080d817aac89dd21cd8992f86a5c229c53df1559f07470b76f291277f3a",
    "last_100_chars_hash": "920cca902d24395854d006bf5deff4224f11ba4013981340e51828dddf7a6d13",
    "total_lines": 1965,
    "total_chars": 69511
  }
}